PythonExtensionsCollection/PythonExtensionsCollection.pdf
PythonExtensionsCollection/__init__.py
PythonExtensionsCollection/version.py
PythonExtensionsCollection/Comparison/CComparison.py
PythonExtensionsCollection/Comparison/__init__.py
PythonExtensionsCollection/File/CFile.py
PythonExtensionsCollection/File/__init__.py
PythonExtensionsCollection/Folder/CFolder.py
PythonExtensionsCollection/Folder/__init__.py
PythonExtensionsCollection/String/CString.py
PythonExtensionsCollection/String/__init__.py
PythonExtensionsCollection/Utils/CUtils.py
PythonExtensionsCollection/Utils/__init__.py
PythonExtensionsCollection-0.16.0.dist-info/LICENSE
PythonExtensionsCollection-0.16.0.dist-info/METADATA
PythonExtensionsCollection-0.16.0.dist-info/WHEEL
PythonExtensionsCollection-0.16.0.dist-info/top_level.txt
PythonExtensionsCollection-0.16.0.dist-info/RECORD
