Metadata-Version: 2.1
Name: PythonExtensionsCollection
Version: 0.16.0
Summary: Additional Python functions
Home-page: https://github.com/test-fullautomation/python-extensions-collection
Author: Holger Queckenstedt
Author-email: Holger.Queckenstedt@de.bosch.com
License: UNKNOWN
Platform: UNKNOWN
Classifier: Programming Language :: Python :: 3
Classifier: License :: OSI Approved :: Apache Software License
Classifier: Operating System :: OS Independent
Classifier: Development Status :: 4 - Beta
Classifier: Intended Audience :: Developers
Classifier: Topic :: Software Development
Requires-Python: >=3.0
License-File: LICENSE
Requires-Dist: dotdict
